{"/LXNxHyefuUajKQCIrN2Iw==":"mbr-1920x1440.png","krQhURdpyHRwvSiCTAYepw==":"mbr-1256x838.jpg","bPea1FME58YDxZkUmaJRcw==":"mbr-596x397.jpg","wyZaTgR8X9VGejiCPXwvXw==":"mbr-1-596x397.jpg","yj65sRuI116jFLEwblFzpQ==":"mbr-4-596x397.jpg","5oPK1SFHulevFYkrYKzJZA==":"mbr-596x447.jpg","avvqA70996b1K9wVBqlPyw==":"mbr-596x401.jpg","pOu5RVJOYUVtoRmCFCuY7Q==":"mbr-1920x1280.jpg","yhM3E1ZFr8dF18pJX8fqCw==":"mbr-1256x837.jpg","w83uDO7df7KKhPdDldUGYg==":"mbr-1-1920x1280.jpg","7+IaZveUPgj7KRGNlBTXbw==":"mbr-816x544.jpg","tCpP3Zby51T46L6MmgZSgA==":"mbr-1-816x544.jpg","lwgOQaWOCTYj+S01nb8m8g==":"mbr-816x524.jpg","8cRf2rMsVHRj++7zzvhg6w==":"mbr-198x198.jpg","hvxIYJbHmr3+Fqg1rCxUZQ==":"mbr-1256x829.jpg","d4jluFEvInSq9opG4soRsg==":"mbr-1920x1279.jpg","GIi3nJff4Ix57XkIFeQSgA==":"mbr-1920x1152.png","rSrzWkgND++up0B1qT44sQ==":"liberty-256-240x240.png","mHdox5EUaQu3pUkY+m99ew==":"mapfre-256-240x240.png","XAe8v8R/ArT4VR5LXLGtJg==":"porto-256-240x240.png","p+Gy0waJwa3caOlz/84w6Q==":"tokio-257-240x240.png","ymcSOO/MPtfPWL902SPfdA==":"bradesco-seguros-240x254.png","3E0XkPMzPHOuLYAec8JI2A==":"sompo-seguros-240x137.png","xAQvdzKQtP+qOjxGHrsSTw==":"allianz-logo-240x156.png","e3qaCSadHqTl8MN07FCN6w==":"hdi-256-240x240.png"}